wallettron/__init__.py
wallettron/main.py
wallettron-0.2.0.dist-info/licenses/LICENSE.txt
wallettron-0.2.0.dist-info/METADATA
wallettron-0.2.0.dist-info/WHEEL
wallettron-0.2.0.dist-info/top_level.txt
wallettron-0.2.0.dist-info/RECORD
