Metadata-Version: 2.4
Name: wallettron
Version: 0.2.0
Summary: wallettron library for Python
Author: fS9TRotId5
License-File: LICENSE.txt
Dynamic: author
Dynamic: description
Dynamic: description-content-type
Dynamic: license-file
Dynamic: summary
